api/__init__.py
pyrex_api-0.1.0.dist-info/METADATA
pyrex_api-0.1.0.dist-info/WHEEL
pyrex_api-0.1.0.dist-info/entry_points.txt
pyrex_api-0.1.0.dist-info/RECORD
